rpmrepo
tests
